nasap_fit_py/__init__.py
nasap_fit_py/fitting/__init__.py
nasap_fit_py/fitting/lmfit/__init__.py
nasap_fit_py/fitting/lmfit/iter_cb.py
nasap_fit_py/fitting/lmfit/objective_func.py
nasap_fit_py/fitting/lmfit/tests/__init__.py
nasap_fit_py/fitting/lmfit/tests/test_iter_cb.py
nasap_fit_py/fitting/lmfit/tests/test_objective_func.py
nasap_fit_py/fitting/objective_func.py
nasap_fit_py/fitting/sample_data/__init__.py
nasap_fit_py/fitting/sample_data/a_to_b.py
nasap_fit_py/fitting/sample_data/sample_data.py
nasap_fit_py/fitting/sample_data/tests/__init__.py
nasap_fit_py/fitting/sample_data/tests/test_a_to_b.py
nasap_fit_py/fitting/sample_data/tests/test_sample_data.py
nasap_fit_py/fitting/tests/__init__.py
nasap_fit_py/fitting/tests/test_objective_func.py
nasap_fit_py/mocks/__init__.py
nasap_fit_py/mocks/mock_fitting.py
nasap_fit_py/mocks/tests/__init__.py
nasap_fit_py/mocks/tests/test_mock_fit.py
nasap_fit_py/ode_creation/__init__.py
nasap_fit_py/ode_creation/csv_to_reactions.py
nasap_fit_py/ode_creation/lib/__init__.py
nasap_fit_py/ode_creation/lib/particle_change.py
nasap_fit_py/ode_creation/lib/tests/__init__.py
nasap_fit_py/ode_creation/lib/tests/test_particle_change.py
nasap_fit_py/ode_creation/reaction_class.py
nasap_fit_py/ode_creation/reactions_to_ode.py
nasap_fit_py/ode_creation/tests/__init__.py
nasap_fit_py/ode_creation/tests/test_csv_to_reactions.py
nasap_fit_py/ode_creation/tests/test_reactions_to_ode.py
nasap_fit_py/py.typed
nasap_fit_py/simulation/__init__.py
nasap_fit_py/simulation/addition.py
nasap_fit_py/simulation/gillespie.py
nasap_fit_py/simulation/simulating_func.py
nasap_fit_py/simulation/simulation_with_addition.py
nasap_fit_py/simulation/tests/__init__.py
nasap_fit_py/simulation/tests/test_addition.py
nasap_fit_py/simulation/tests/test_gillespie.py
nasap_fit_py/simulation/tests/test_simulating_func.py
nasap_fit_py/simulation/tests/test_simulation_with_addition.py
nasap_fit_py/simulation/utils/__init__.py
nasap_fit_py/simulation/utils/alias_id.py
nasap_fit_py-0.3.2.dist-info/LICENSE
nasap_fit_py-0.3.2.dist-info/METADATA
nasap_fit_py-0.3.2.dist-info/WHEEL
nasap_fit_py-0.3.2.dist-info/RECORD
